rtedata/__init__.py
rtedata/catalog.py
rtedata/client.py
rtedata/retriever.py
rtedata/tools.py
rtedata-1.0.5.dist-info/licenses/LICENSE
rtedata-1.0.5.dist-info/METADATA
rtedata-1.0.5.dist-info/WHEEL
rtedata-1.0.5.dist-info/top_level.txt
rtedata-1.0.5.dist-info/RECORD
