Metadata-Version: 2.4
Name: rtedata
Version: 1.0.5
Summary: Python wrapper for RTE API requests
Author-email: Henri Upton <henriupton99@gmail.com>
License-Expression: MIT
Project-URL: Homepage, https://github.com/henriupton99/rtedata
Project-URL: Issues, https://github.com/henriupton99/rtedata/issues
Classifier: Programming Language :: Python :: 3.10
Classifier: Operating System :: OS Independent
Requires-Python: >=3.10
License-File: LICENSE
Requires-Dist: pandas>=2.2.3
Requires-Dist: requests>=2.32.3
Dynamic: license-file
